umami_preprocessing-0.2.8.dist-info/licenses/LICENSE
upp/__init__.py
upp/main.py
upp/classes/__init__.py
upp/classes/components.py
upp/classes/preprocessing_config.py
upp/classes/region.py
upp/classes/resampling_config.py
upp/classes/reweight_config.py
upp/classes/variable_config.py
upp/stages/__init__.py
upp/stages/hist.py
upp/stages/interpolation.py
upp/stages/merging.py
upp/stages/normalisation.py
upp/stages/plot.py
upp/stages/resampling.py
upp/stages/reweight.py
upp/stages/rw_merge.py
upp/stages/split_containers.py
upp/utils/__init__.py
upp/utils/check_input_samples.py
upp/utils/logger.py
upp/utils/tools.py
umami_preprocessing-0.2.8.dist-info/METADATA
umami_preprocessing-0.2.8.dist-info/WHEEL
umami_preprocessing-0.2.8.dist-info/entry_points.txt
umami_preprocessing-0.2.8.dist-info/top_level.txt
umami_preprocessing-0.2.8.dist-info/RECORD
